phoenixSM4/__init__.py
phoenixSM4-0.0.1.dist-info/LICENSE
phoenixSM4-0.0.1.dist-info/METADATA
phoenixSM4-0.0.1.dist-info/WHEEL
phoenixSM4-0.0.1.dist-info/top_level.txt
phoenixSM4-0.0.1.dist-info/RECORD
