Metadata-Version: 2.1
Name: phoenixSM4
Version: 0.0.1
Summary: tool to perform differential fault analysis attacks (DFA) against SM4
Home-page: https://github.com/SideChannelMarvels/JeanGrey
Author: Sylvain Pelissier
Author-email: sylvain.pelissier@gmail.com
Classifier: Programming Language :: Python :: 3
Classifier: License :: OSI Approved :: GNU General Public License v3 or later (GPLv3+)
Classifier: Operating System :: OS Independent
Classifier: Development Status :: 4 - Beta
Classifier: Intended Audience :: Science/Research
Classifier: Topic :: Security :: Cryptography
License-File: LICENSE
